flamingo_light_sdk/__init__.py
flamingo_light_sdk/control_rate.py
flamingo_light_sdk/classes/joystick/__init__.py
flamingo_light_sdk/classes/joystick/joystick.cpython-310-aarch64-linux-gnu.so
flamingo_light_sdk/classes/logger/__init__.py
flamingo_light_sdk/classes/logger/logger.cpython-310-aarch64-linux-gnu.so
flamingo_light_sdk/classes/mode/__init__.py
flamingo_light_sdk/classes/mode/libonnxruntime.so
flamingo_light_sdk/classes/mode/libonnxruntime.so.1
flamingo_light_sdk/classes/mode/libonnxruntime.so.1.23.0
flamingo_light_sdk/classes/mode/libonnxruntime_providers_shared.so
flamingo_light_sdk/classes/mode/mode.cpython-310-aarch64-linux-gnu.so
flamingo_light_sdk/classes/onnxpolicy/__init__.py
flamingo_light_sdk/classes/onnxpolicy/libonnxruntime.so
flamingo_light_sdk/classes/onnxpolicy/libonnxruntime.so.1
flamingo_light_sdk/classes/onnxpolicy/libonnxruntime.so.1.23.0
flamingo_light_sdk/classes/onnxpolicy/libonnxruntime_providers_shared.so
flamingo_light_sdk/classes/onnxpolicy/onnxpolicy.cpython-310-aarch64-linux-gnu.so
flamingo_light_sdk/classes/rl/__init__.py
flamingo_light_sdk/classes/rl/rl.cpython-310-aarch64-linux-gnu.so
flamingo_light_sdk/classes/robot/__init__.py
flamingo_light_sdk/classes/robot/robot.cpython-310-aarch64-linux-gnu.so
flamingo_light_sdk/example/example_policy.onnx
flamingo_light_sdk/example/example_run.py
flamingo_light_sdk-0.1.0.dist-info/METADATA
flamingo_light_sdk-0.1.0.dist-info/WHEEL
flamingo_light_sdk-0.1.0.dist-info/top_level.txt
flamingo_light_sdk-0.1.0.dist-info/RECORD
