Metadata-Version: 2.4
Name: flamingo-light-sdk
Version: 0.1.0
Summary: Flamingo Light SDK package
Author-email: JW KIM <rnd@cocelo.ai>
Classifier: Programming Language :: Python :: 3.10
Classifier: Operating System :: POSIX :: Linux
Requires-Python: ==3.10.*
